__init__.py
audio_classifier.py
audio_file_analysing.py
main.py
read_wav.py
spec_functions.py
white_noise.py
wiener_parameters_calculation.py
working_example_of_spec.py
group_B_audio_analyzer-0.0.3.dist-info/METADATA
group_B_audio_analyzer-0.0.3.dist-info/WHEEL
group_B_audio_analyzer-0.0.3.dist-info/top_level.txt
group_B_audio_analyzer-0.0.3.dist-info/RECORD
