Metadata-Version: 2.1
Name: group-B-audio-analyzer
Version: 0.0.3
Summary: A Python package for audio analysis and .wav file classification.
Author-email: Agustin Silva <agustinsilva447@gmail.com>, "Mahtab T. Nejad " <mahtabnejadt@gmail.com>, Mahdi Rasouli <mahdi.rasouli77@gmail.com>, Paula Oliveri <olicarpa@gmail.com>
Project-URL: Homepage, https://example.com
Project-URL: Documentation, https://readthedocs.org
Project-URL: Repository, https://git.smr3696.ictp.it/Mahdi/group_b_audio_analyzer
Keywords: Advent of Code,captcha
Classifier: Programming Language :: Python :: 3
Classifier: License :: OSI Approved :: GNU General Public License v3 (GPLv3)
Classifier: Operating System :: OS Independent
Requires-Python: >=3.8
Requires-Dist: numpy
Requires-Dist: scipy
Requires-Dist: matplotlib
